README.txt
setup.py
faadata/__init__.py
faadata/urls.py
faadata.egg-info/PKG-INFO
faadata.egg-info/SOURCES.txt
faadata.egg-info/dependency_links.txt
faadata.egg-info/top_level.txt
faadata/aircraft/__init__.py
faadata/aircraft/admin.py
faadata/aircraft/geocode.py
faadata/aircraft/load.py
faadata/aircraft/models.py
faadata/aircraft/parser.py
faadata/aircraft/tests.py
faadata/aircraft/urls.py
faadata/aircraft/views.py
faadata/aircraft/management/__init__.py
faadata/aircraft/management/commands/__init__.py
faadata/aircraft/management/commands/aircraft_import.py
faadata/aircraft/migrations/0001_initial.py
faadata/aircraft/migrations/__init__.py
faadata/aircraft/south_migrations/0001_initial.py
faadata/aircraft/south_migrations/0002_add_expiration_date.py
faadata/aircraft/south_migrations/0003_add_n_number_index.py
faadata/aircraft/south_migrations/0004_resize_status_code.py
faadata/aircraft/south_migrations/0005_add_geocode_type_and_date.py
faadata/aircraft/south_migrations/0006_add_november_2013_field_additions.py
faadata/aircraft/south_migrations/__init__.py
faadata/airports/__init__.py
faadata/airports/admin.py
faadata/airports/load.py
faadata/airports/models.py
faadata/airports/tests.py
faadata/airports/urls.py
faadata/airports/utils.py
faadata/airports/views.py
faadata/airports/management/__init__.py
faadata/airports/management/commands/__init__.py
faadata/airports/management/commands/airport_import.py
faadata/airports/management/commands/ourairports_import.py
faadata/airports/migrations/0001_initial.py
faadata/airports/migrations/0002_auto_20160521_0033.py
faadata/airports/migrations/0003_auto_20170817_2343.py
faadata/airports/migrations/__init__.py
faadata/airports/south_migrations/0001_initial.py
faadata/airports/south_migrations/0002_add_field_airport_facility_type.py
faadata/airports/south_migrations/0002_add_fields_for_more_airport_info.py
faadata/airports/south_migrations/0003_add_state_post_office_code.py
faadata/airports/south_migrations/0004_match_fadds_format_changes.py
faadata/airports/south_migrations/0005_location_identifier_unique.py
