Metadata-Version: 1.1
Name: faadata
Version: 1.1.0
Summary: Models and load scripts used to import FAA (and FADDS) data into Django
Home-page: https://github.com/adamfast/faadata
Author: Adam Fast
Author-email: adamfast@gmail.com
License: UNKNOWN
Platform: UNKNOWN
Classifier: Development Status :: 5 - Production/Stable
Classifier: Environment :: Web Environment
Classifier: Framework :: Django
Classifier: Intended Audience :: Developers
Classifier: License :: OSI Approved :: BSD License
Classifier: Operating System :: OS Independent
Classifier: Programming Language :: Python
Classifier: Topic :: Utilities
